{"ra": "136.363129", "dec": "44.143883", "redshift": "0.053335", "SDSS dr7 id": "587731681193754794", "Common name": "Unknown", "NSA id": "145910", "Estimated distance": "0.053488921374082565 * c / H_0", "Petrosian radius (degrees)": "9.652617", "Run": "2740", "Camcol": "5", "Field": "220", "Rerun": "301", "Sersic axis ratio": "0.518768", "Url to view": "[View on SkyServer](+tab+http://skyserver.sdss.org/dr14/en/tools/chart/navi.aspx?ra=136.36312866210938&dec=44.143882751464844&opt=F)", "#isModelling": true, "#models": [{"frame": 0, "model": "GALAXY_BUILDER_DIFFERENCE"}, {"frame": 2, "model": "GALAXY_BUILDER_MODEL"}]}